build/lib/vkbottle_kids/main.py
build/lib/vkbottle_kids/setup.py
build/lib/vkbottle_kids/kid_bot/__init__.py
build/lib/vkbottle_kids/kid_bot/bot.py
vkbottle_kids/main.py
vkbottle_kids/setup.py
vkbottle_kids/kid_bot/__init__.py
vkbottle_kids/kid_bot/bot.py
vkbottle_kids-0.0.11.dist-info/METADATA
vkbottle_kids-0.0.11.dist-info/WHEEL
vkbottle_kids-0.0.11.dist-info/top_level.txt
vkbottle_kids-0.0.11.dist-info/RECORD
