Metadata-Version: 2.1
Name: vkbottle-kids
Version: 0.0.11
Author: Alexsey Githabovich
Requires-Dist: vkbottle (>=4.3.10)
